fgbio_postprocessing/__init__.py
fgbio_postprocessing/cli.py
fgbio_postprocessing/simplex_filter.py
fgbio_postprocessing-0.1.8.dist-info/AUTHORS.rst
fgbio_postprocessing-0.1.8.dist-info/LICENSE
fgbio_postprocessing-0.1.8.dist-info/METADATA
fgbio_postprocessing-0.1.8.dist-info/WHEEL
fgbio_postprocessing-0.1.8.dist-info/entry_points.txt
fgbio_postprocessing-0.1.8.dist-info/top_level.txt
fgbio_postprocessing-0.1.8.dist-info/RECORD
