Metadata-Version: 2.1
Name: fgbio-postprocessing
Version: 0.1.8
Summary: fgbio_postprocessing
Home-page: https://github.com/ionox0/fgbio_postprocessing
Author: ian johnson
Author-email: ionox0@gmail.com
License: MIT license
Keywords: fgbio_postprocessing
Platform: UNKNOWN
Classifier: Development Status :: 2 - Pre-Alpha
Classifier: Intended Audience :: Developers
Classifier: Operating System :: OS Independent
Classifier: License :: OSI Approved :: MIT License
Classifier: Natural Language :: English
Classifier: Programming Language :: Python :: 3
Classifier: Programming Language :: Python :: 3.5
Classifier: Programming Language :: Python :: 3.6
Classifier: Programming Language :: Python :: 3.7
Classifier: Programming Language :: Python :: 3.8
Requires-Python: >=3.5
Requires-Dist: click (==7.1.2)
Requires-Dist: pysam (==0.15.4)
